encoding/__init__.py
encoding/parallel.py
encoding/version.py
encoding/datasets/__init__.py
encoding/datasets/ade20k.py
encoding/datasets/base.py
encoding/datasets/cityscapes.py
encoding/datasets/cityscapescoarse.py
encoding/datasets/coco.py
encoding/datasets/folder.py
encoding/datasets/hpw18.py
encoding/datasets/imagenet.py
encoding/datasets/minc.py
encoding/datasets/pascal_aug.py
encoding/datasets/pascal_voc.py
encoding/datasets/pcontext.py
encoding/functions/__init__.py
encoding/functions/customize.py
encoding/functions/dist_syncbn.py
encoding/functions/encoding.py
encoding/functions/rectify.py
encoding/functions/syncbn.py
encoding/lib/__init__.py
encoding/lib/cpu/encoding_cpu.cpp
encoding/lib/cpu/nms_cpu.cpp
encoding/lib/cpu/operator.cpp
encoding/lib/cpu/operator.h
encoding/lib/cpu/rectify_cpu.cpp
encoding/lib/cpu/roi_align_cpu.cpp
encoding/lib/cpu/syncbn_cpu.cpp
encoding/lib/gpu/activation_kernel.cu
encoding/lib/gpu/common.h
encoding/lib/gpu/device_tensor.h
encoding/lib/gpu/encoding_kernel.cu
encoding/lib/gpu/lib_ssd.cu
encoding/lib/gpu/nms_kernel.cu
encoding/lib/gpu/operator.cpp
encoding/lib/gpu/operator.h
encoding/lib/gpu/rectify_cuda.cu
encoding/lib/gpu/roi_align_kernel.cu
encoding/lib/gpu/syncbn_kernel.cu
encoding/models/__init__.py
encoding/models/deepten.py
encoding/models/model_store.py
encoding/models/model_zoo.py
encoding/models/backbone/__init__.py
encoding/models/backbone/resnest.py
encoding/models/backbone/resnet.py
encoding/models/backbone/resnet_variants.py
encoding/models/backbone/resnext.py
encoding/models/backbone/wideresnet.py
encoding/models/backbone/xception.py
encoding/models/sseg/__init__.py
encoding/models/sseg/atten.py
encoding/models/sseg/base.py
encoding/models/sseg/deeplab.py
encoding/models/sseg/encnet.py
encoding/models/sseg/fcfpn.py
encoding/models/sseg/fcn.py
encoding/models/sseg/psp.py
encoding/models/sseg/upernet.py
encoding/nn/__init__.py
encoding/nn/attention.py
encoding/nn/customize.py
encoding/nn/dropblock.py
torch_encoding-1.2.1.dist-info/LICENSE
torch_encoding-1.2.1.dist-info/METADATA
torch_encoding-1.2.1.dist-info/WHEEL
torch_encoding-1.2.1.dist-info/top_level.txt
torch_encoding-1.2.1.dist-info/RECORD
