Metadata-Version: 2.1
Name: torch-encoding
Version: 1.2.1
Summary: PyTorch Encoding Package
Home-page: https://github.com/zhanghang1989/PyTorch-Encoding
Author: Hang Zhang
Author-email: zhanghang0704@gmail.com
License: MIT
Platform: UNKNOWN
Requires-Dist: numpy
Requires-Dist: tqdm
Requires-Dist: nose
Requires-Dist: portalocker
Requires-Dist: torch (>=1.4.0)
Requires-Dist: torchvision (>=0.5.0)
Requires-Dist: Pillow
Requires-Dist: scipy
Requires-Dist: requests
